{
"--primary": "#365e7766",
"--secondary": "#17516fd9 linear-gradient(135deg, rgba(0,0,0,0.4) 0%, rgba(27,66,84,0.4) 30%, rgba(31,97,131,0.4) 100%)",
"--highlight": "#4b8ea2",
"--background": "#0a171d",
"--bgSize": "100% 100%", 
"--bgAnim": "none",
"--container": "linear-gradient(202deg, rgba(0,41,54,1) 0%, rgba(55,114,145,0.5) 35%, rgba(198,222,218,0.4) 100%)",
"--border": "3px solid #030F1599",
"--hoverborder": "solid #2d5066 3px",
"--acolor": "ghostwhite",
"--ahover": "#3f86a9",
"--bcolor": "#eff",
"--pcolor": "#fbf9f7",
"--themelink": "ghostwhite",
"--header": "#2d5066",
"--hsub": "#3a6483",
"--textshadowprimary": "0px 2px 4px #dfeef1",
"--textshadowsecondary": "1px 1px 1px black",
"--commentprimary": "#365e7755",
"--commentsecondary": "#086a9f55",
"--commentborder": "solid black 2px",
"--country": "retrofuturism",
"--image": "url(https://cdn.discordapp.com/attachments/661461905419796501/1045494620425027675/image.png)",
"--height": "300",
"--filter": "sepia(200%) hue-rotate(160deg) saturate(130%) brightness(105%)",
"songName": ["Neil Cicierega - Geocities (Bonus Track)","Zodiac (Eponymous)","Daft Punk - Aerodynamic"],
"songURL": ["https://cdn.discordapp.com/attachments/661461905419796501/1045491456544079872/Neil_Cicierega_-_Geocities_Bonus_Track.mp3","https://cdn.discordapp.com/attachments/661461905419796501/1045492301541154927/Zodiac_Eponymous.mp3","https://cdn.discordapp.com/attachments/661461905419796501/1045495158277423125/Daft_Punk_-_Aerodynamic.mp3"]
}
